Metadata-Version: 1.1
Name: cfncluster-node-fork-hcluster
Version: 1.3.5.1
Summary: cfncluster-node-fork_hcluster is a fork from cfncluster-node to provide aa support for heterogenous clusters. cfncluster-node provides the scripts for a cfncluster node.
Home-page: https://github.com/f403/cfncluster-node-fork_hcluster
Author: Oleksandr Shcherbakov
Author-email: admin@sp06n.org.ua
License: Amazon Software License
Platform: UNKNOWN
Classifier: Development Status :: 3 - Alpha
Classifier: Environment :: Console
Classifier: Programming Language :: Python
Classifier: Topic :: Scientific/Engineering
Classifier: License :: Other/Proprietary License
